gedcomx/__init__.py
gedcomx/date.py
gedcomx/enums.py
gedcomx/fileformat.py
gedcomx/models.py
gedcomx/utils.py
pygedcomx-0.0.1.dist-info/LICENSE
pygedcomx-0.0.1.dist-info/WHEEL
pygedcomx-0.0.1.dist-info/METADATA
pygedcomx-0.0.1.dist-info/RECORD
